fpga/t9_timer.v
module t9_timer #(
    parameter CLK_FREQ = 27000000
) (
    input wire clk,
    input wire reset,
    input wire start,
    output reg timeout
);
    localparam COUNT_MAX = CLK_FREQ / 2;
    reg [24:0] counter;

    always @(posedge clk or posedge reset) begin
        if (reset) begin
            counter <= 25'd0;
            timeout <= 1'b0;
        end else if (start) begin
            if (counter >= COUNT_MAX) begin
                timeout <= 1'b1;
                counter <= counter;
            end else begin
                counter <= counter + 1'b1;
                timeout <= 1'b0;
            end
        end else begin
            counter <= 25'd0;
            timeout <= 1'b0;
        end
    end
endmodule

fpga/t9_key_fsm.v
module t9_key_fsm (
    input wire clk,
    input wire reset,
    input wire key_pressed_strobe,
    output reg [1:0] char_index,
    output reg commit_pulse
);
    localparam STATE_IDLE = 2'b00;
    localparam STATE_KEY_COUNT = 2'b01;
    localparam STATE_COMMIT = 2'b10;

    reg [1:0] current_state, next_state;
    reg start_timer;
    wire timer_timeout;

    t9_timer #(.CLK_FREQ(100)) u_timer (
        .clk(clk),
        .reset(reset),
        .start(start_timer),
        .timeout(timer_timeout)
    );

    always @(posedge clk or posedge reset) begin
        if (reset)
            current_state <= STATE_IDLE;
        else
            current_state <= next_state;    
    end

    always @(*) begin
        next_state = current_state;
        
        case (current_state)
            STATE_IDLE: begin
                if (key_pressed_strobe)
                    next_state = STATE_KEY_COUNT;
            end

            STATE_KEY_COUNT: begin
                if (timer_timeout)
                    next_state = STATE_COMMIT;
            end
            STATE_COMMIT: begin
                next_state = STATE_COMMIT;
            end 
            default:
                next_state = STATE_IDLE; 
        endcase
    end

    always @(posedge clk or posedge reset) begin
        if (reset) begin
            char_index <= 2'b00;
            commit_pulse <= 1'b0;
            start_timer <= 1'b0;
        end else begin
            commit_pulse <= 1'b0;

            case (current_state)
                STATE_IDLE: begin
                    if (key_pressed_strobe) begin
                        char_index <= 2'b00;
                        start_timer <= 1'b1;
                    end else begin
                        start_timer <= 1'b0;
                    end
                end

                STATE_KEY_COUNT: begin
                    if (key_pressed_strobe) begin
                        if (char_index == 2'b10)
                            char_index <= 2'b00;
                        else
                            char_index <= char_index + 1'b1;
                    
                        start_timer <= 1'b0;
                    end else begin
                        start_timer <= 1'b1;
                    end
                end

                STATE_COMMIT: begin
                    commit_pulse <= 1'b1;
                    start_timer <= 1'b0;
                end
            endcase
        end
    end
endmodule

fpga/t9_key_fsm_tb.v
`timescale 1ns / 1ps

module t9_key_fsm_tb;
    reg clk;
    reg reset;
    reg key_pressed_strobe;
    wire [1:0] char_index;
    wire commit_pulse;

    t9_key_fsm uut (
        .clk(clk),
        .reset(reset),
        .key_pressed_strobe(key_pressed_strobe),
        .char_index(char_index),
        .commit_pulse(commit_pulse)
    );
    
    always #18.5 clk = ~clk;

    initial begin
        $dumpfile("t9_key_fsm_tb.vcd");
        $dumpvars(0, t9_key_fsm_tb);

        clk = 0; reset = 1; key_pressed_strobe = 0;
        #100; reset = 0; #50;

        key_pressed_strobe = 1; #37; key_pressed_strobe = 0;
        #100;
        key_pressed_strobe = 1; #37; key_pressed_strobe = 0;
        #100;
        key_pressed_strobe = 1; #37; key_pressed_strobe = 0;
        #100;

        @(posedge commit_pulse);
        $display("Sucesso: Letra confirmada com índice=%b", char_index);

        #500
        $finish;
    end
endmodule

fpga/t9_key_fsm_tb.vcd
$date
	Fri Aug  7 15:25:18 2026
$end
$version
	Icarus Verilog
$end
$timescale
	1ps
$end
$scope module t9_key_fsm_tb $end
$var wire 1 ! commit_pulse $end
$var wire 2 " char_index [1:0] $end
$var reg 1 # clk $end
$var reg 1 $ key_pressed_strobe $end
$var reg 1 % reset $end
$scope module uut $end
$var wire 1 # clk $end
$var wire 1 $ key_pressed_strobe $end
$var wire 1 % reset $end
$var wire 1 & timer_timeout $end
$var parameter 2 ' STATE_COMMIT $end
$var parameter 2 ( STATE_IDLE $end
$var parameter 2 ) STATE_KEY_COUNT $end
$var reg 2 * char_index [1:0] $end
$var reg 1 ! commit_pulse $end
$var reg 2 + current_state [1:0] $end
$var reg 2 , next_state [1:0] $end
$var reg 1 - start_timer $end
$scope module u_timer $end
$var wire 1 # clk $end
$var wire 1 % reset $end
$var wire 1 - start $end
$var parameter 32 . CLK_FREQ $end
$var parameter 32 / COUNT_MAX $end
$var reg 25 0 counter [24:0] $end
$var reg 1 & timeout $end
$upscope $end
$upscope $end
$upscope $end
$enddefinitions $end
$comment Show the parameter values. $end
$dumpall
b110010 /
b1100100 .
b1 )
b0 (
b10 '
$end
#0
$dumpvars
b0 0
0-
b0 ,
b0 +
b0 *
0&
1%
0$
0#
b0 "
0!
$end
#18500
1#
#37000
0#
#55500
1#
#74000
0#
#92500
1#
#100000
0%
#111000
0#
#129500
1#
#148000
0#
#150000
b1 ,
1$
#166500
1-
b1 +
1#
#185000
0#
#187000
0$
#203500
b1 0
1#
#222000
0#
#240500
b10 0
1#
#259000
0#
#277500
b11 0
1#
#287000
1$
#296000
0#
#314500
0-
b1 "
b1 *
b100 0
1#
#324000
0$
#333000
0#
#351500
b0 0
1-
1#
#370000
0#
#388500
b1 0
1#
#407000
0#
#424000
1$
#425500
b10 0
0-
b10 "
b10 *
1#
#444000
0#
#461000
0$
#462500
1-
b0 0
1#
#481000
0#
#499500
b1 0
1#
#518000
0#
#536500
b10 0
1#
#555000
0#
#573500
b11 0
1#
#592000
0#
#610500
b100 0
1#
#629000
0#
#647500
b101 0
1#
#666000
0#
#684500
b110 0
1#
#703000
0#
#721500
b111 0
1#
#740000
0#
#758500
b1000 0
1#
#777000
0#
#795500
b1001 0
1#
#814000
0#
#832500
b1010 0
1#
#851000
0#
#869500
b1011 0
1#
#888000
0#
#906500
b1100 0
1#
#925000
0#
#943500
b1101 0
1#
#962000
0#
#980500
b1110 0
1#
#999000
0#
#1017500
b1111 0
1#
#1036000
0#
#1054500
b10000 0
1#
#1073000
0#
#1091500
b10001 0
1#
#1110000
0#
#1128500
b10010 0
1#
#1147000
0#
#1165500
b10011 0
1#
#1184000
0#
#1202500
b10100 0
1#
#1221000
0#
#1239500
b10101 0
1#
#1258000
0#
#1276500
b10110 0
1#
#1295000
0#
#1313500
b10111 0
1#
#1332000
0#
#1350500
b11000 0
1#
#1369000
0#
#1387500
b11001 0
1#
#1406000
0#
#1424500
b11010 0
1#
#1443000
0#
#1461500
b11011 0
1#
#1480000
0#
#1498500
b11100 0
1#
#1517000
0#
#1535500
b11101 0
1#
#1554000
0#
#1572500
b11110 0
1#
#1591000
0#
#1609500
b11111 0
1#
#1628000
0#
#1646500
b100000 0
1#
#1665000
0#
#1683500
b100001 0
1#
#1702000
0#
#1720500
b100010 0
1#
#1739000
0#
#1757500
b100011 0
1#
#1776000
0#
#1794500
b100100 0
1#
#1813000
0#
#1831500
b100101 0
1#
#1850000
0#
#1868500
b100110 0
1#
#1887000
0#
#1905500
b100111 0
1#
#1924000
0#
#1942500
b101000 0
1#
#1961000
0#
#1979500
b101001 0
1#
#1998000
0#
#2016500
b101010 0
1#
#2035000
0#
#2053500
b101011 0
1#
#2072000
0#
#2090500
b101100 0
1#
#2109000
0#
#2127500
b101101 0
1#
#2146000
0#
#2164500
b101110 0
1#
#2183000
0#
#2201500
b101111 0
1#
#2220000
0#
#2238500
b110000 0
1#
#2257000
0#
#2275500
b110001 0
1#
#2294000
0#
#2312500
b110010 0
1#
#2331000
0#
#2349500
b10 ,
1&
1#
#2368000
0#
#2386500
b10 +
1#
#2405000
0#
#2423500
0-
1!
1#
#2442000
0#
#2460500
1!
0&
b0 0
1#
#2479000
0#
#2497500
1!
1#
#2516000
0#
#2534500
1!
1#
#2553000
0#
#2571500
1!
1#
#2590000
0#
#2608500
1!
1#
#2627000
0#
#2645500
1!
1#
#2664000
0#
#2682500
1!
1#
#2701000
0#
#2719500
1!
1#
#2738000
0#
#2756500
1!
1#
#2775000
0#
#2793500
1!
1#
#2812000
0#
#2830500
1!
1#
#2849000
0#
#2867500
1!
1#
#2886000
0#
#2904500
1!
1#
